airflow/providers/standard/LICENSE
airflow/providers/standard/__init__.py
airflow/providers/standard/get_provider_info.py
airflow/providers/standard/version_compat.py
airflow/providers/standard/decorators/__init__.py
airflow/providers/standard/decorators/bash.py
airflow/providers/standard/decorators/branch_external_python.py
airflow/providers/standard/decorators/branch_python.py
airflow/providers/standard/decorators/branch_virtualenv.py
airflow/providers/standard/decorators/external_python.py
airflow/providers/standard/decorators/python.py
airflow/providers/standard/decorators/python_virtualenv.py
airflow/providers/standard/decorators/sensor.py
airflow/providers/standard/decorators/short_circuit.py
airflow/providers/standard/hooks/__init__.py
airflow/providers/standard/hooks/filesystem.py
airflow/providers/standard/hooks/package_index.py
airflow/providers/standard/hooks/subprocess.py
airflow/providers/standard/operators/__init__.py
airflow/providers/standard/operators/bash.py
airflow/providers/standard/operators/branch.py
airflow/providers/standard/operators/datetime.py
airflow/providers/standard/operators/empty.py
airflow/providers/standard/operators/latest_only.py
airflow/providers/standard/operators/python.py
airflow/providers/standard/operators/smooth.py
airflow/providers/standard/operators/trigger_dagrun.py
airflow/providers/standard/operators/weekday.py
airflow/providers/standard/sensors/__init__.py
airflow/providers/standard/sensors/bash.py
airflow/providers/standard/sensors/date_time.py
airflow/providers/standard/sensors/external_task.py
airflow/providers/standard/sensors/filesystem.py
airflow/providers/standard/sensors/python.py
airflow/providers/standard/sensors/time.py
airflow/providers/standard/sensors/time_delta.py
airflow/providers/standard/sensors/weekday.py
airflow/providers/standard/triggers/__init__.py
airflow/providers/standard/triggers/external_task.py
airflow/providers/standard/triggers/file.py
airflow/providers/standard/triggers/temporal.py
apache_airflow_providers_standard-0.4.0.dist-info/entry_points.txt
apache_airflow_providers_standard-0.4.0.dist-info/WHEEL
apache_airflow_providers_standard-0.4.0.dist-info/METADATA
apache_airflow_providers_standard-0.4.0.dist-info/RECORD
